genesis_mcp_core/__init__.py
genesis_mcp_core/cli/__init__.py
genesis_mcp_core/cli/create.py
genesis_mcp_core/cli/main.py
genesis_mcp_core/cli/templates.py
genesis_mcp_core/core/__init__.py
genesis_mcp_core/core/autonomize_bridge.py
genesis_mcp_core/core/config.py
genesis_mcp_core/core/registry.py
genesis_mcp_core/core/server.py
genesis_mcp_core/templates/basic/.gitignore
genesis_mcp_core/templates/basic/Dockerfile
genesis_mcp_core/templates/basic/Makefile
genesis_mcp_core/templates/basic/README.md
genesis_mcp_core/templates/basic/azure-devops/build-template.yml
genesis_mcp_core/templates/basic/azure-devops/cicd.yaml
genesis_mcp_core/templates/basic/azure-devops/helmpublish.yml
genesis_mcp_core/templates/basic/azure-devops/release-template.yml
genesis_mcp_core/templates/basic/azure-devops/sonar.yml
genesis_mcp_core/templates/basic/azure-devops/version.yml
genesis_mcp_core/templates/basic/connectors/README.md
genesis_mcp_core/templates/basic/connectors/encoder.json
genesis_mcp_core/templates/basic/env.example
genesis_mcp_core/templates/basic/helmcharts/{{ SERVICE_NAME }}/Chart.yaml
genesis_mcp_core/templates/basic/helmcharts/{{ SERVICE_NAME }}/templates/NOTES.txt
genesis_mcp_core/templates/basic/helmcharts/{{ SERVICE_NAME }}/templates/_helpers.tpl
genesis_mcp_core/templates/basic/helmcharts/{{ SERVICE_NAME }}/templates/deployment.yaml
genesis_mcp_core/templates/basic/helmcharts/{{ SERVICE_NAME }}/templates/hpa.yaml
genesis_mcp_core/templates/basic/helmcharts/{{ SERVICE_NAME }}/templates/ingress.yaml
genesis_mcp_core/templates/basic/helmcharts/{{ SERVICE_NAME }}/templates/service.yaml
genesis_mcp_core/templates/basic/helmcharts/{{ SERVICE_NAME }}/templates/serviceaccount.yaml
genesis_mcp_core/templates/basic/helmcharts/{{ SERVICE_NAME }}/values.yaml
genesis_mcp_core/templates/basic/main.py
genesis_mcp_core/templates/basic/pyproject.toml
genesis_mcp_core/templates/basic/template.info
genesis_mcp_core/templates/basic/test_mcp_client.py
genesis_mcp_core-0.0.11.dist-info/METADATA
genesis_mcp_core-0.0.11.dist-info/WHEEL
genesis_mcp_core-0.0.11.dist-info/entry_points.txt
genesis_mcp_core-0.0.11.dist-info/RECORD
