Metadata-Version: 2.3
Name: genesis-mcp-core
Version: 0.0.11
Summary: Genesis MCP Core - A powerful Model Context Protocol server SDK with built-in connector support
License: MIT
Keywords: mcp,model-context-protocol,ai,llm,connector,sdk
Author: Your Name
Author-email: your.email@example.com
Requires-Python: >=3.12,<3.13
Classifier: Development Status :: 4 - Beta
Classifier: Intended Audience :: Developers
Classifier: License :: OSI Approved :: MIT License
Classifier: Programming Language :: Python :: 3
Classifier: Programming Language :: Python :: 3.12
Classifier: Topic :: Scientific/Engineering :: Artificial Intelligence
Classifier: Topic :: Software Development :: Libraries :: Python Modules
Requires-Dist: autonomize-connector-sdk (>=0.2.0,<0.3.0)
Requires-Dist: click (>=8.1.0,<9.0.0)
Requires-Dist: fastapi (>=0.115.0,<0.116.0)
Requires-Dist: httpx (>=0.28.0,<0.29.0)
Requires-Dist: jinja2 (>=3.1.0,<4.0.0)
Requires-Dist: pydantic (>=2.10.0,<3.0.0)
Requires-Dist: pydantic-settings (>=2.6.0,<3.0.0)
Requires-Dist: python-dotenv (>=1.0.0,<2.0.0)
Requires-Dist: structlog (>=24.4.0,<25.0.0)
Requires-Dist: uvicorn[standard] (>=0.32.0,<0.33.0)
Project-URL: Homepage, https://github.com/your-org/genesis-mcp-core
Project-URL: Repository, https://github.com/your-org/genesis-mcp-core
